pydiver/__init__.py
pydiver/pydiver.py
pydiver/version.py
python_diver-1.0.dist-info/LICENSE
python_diver-1.0.dist-info/METADATA
python_diver-1.0.dist-info/WHEEL
python_diver-1.0.dist-info/top_level.txt
python_diver-1.0.dist-info/RECORD
